Mopidy_WebSettings-0.2.0.dist-info/DESCRIPTION.rst
Mopidy_WebSettings-0.2.0.dist-info/METADATA
Mopidy_WebSettings-0.2.0.dist-info/RECORD
Mopidy_WebSettings-0.2.0.dist-info/WHEEL
Mopidy_WebSettings-0.2.0.dist-info/entry_points.txt
Mopidy_WebSettings-0.2.0.dist-info/metadata.json
Mopidy_WebSettings-0.2.0.dist-info/top_level.txt
mopidy_websettings/__init__.py
mopidy_websettings/__init__.pyc
mopidy_websettings/ext.conf
mopidy_websettings/index.html
mopidy_websettings/settingsspec.ini
