Metadata-Version: 2.0
Name: Mopidy-WebSettings
Version: 0.2.0
Summary: Mopidy extension for editing settings in a webinterface
Home-page: https://github.com/woutervanwijk/mopidy-websettings
Author: Wouter van Wijk
Author-email: woutervanwijk@gmail.com
License: Apache License, Version 2.0
Platform: UNKNOWN
Classifier: Environment :: No Input/Output (Daemon)
Classifier: Intended Audience :: End Users/Desktop
Classifier: License :: OSI Approved :: Apache Software License
Classifier: Operating System :: OS Independent
Classifier: Programming Language :: Python :: 2
Classifier: Topic :: Multimedia :: Sound/Audio :: Players
Requires-Dist: ConfigObj (>=4.0.0)
Requires-Dist: Jinja2 (>=2.7)
Requires-Dist: Mopidy (>=0.19)
Requires-Dist: Pykka (>=1.1)
Requires-Dist: setuptools
